[{"t":1752868800,"category":"market-structure","title":"Monthly options expiry (OpEx)","assets":["SPX","NDX"],"scheduled":true},{"t":1755288000,"category":"market-structure","title":"Monthly options expiry (OpEx)","assets":["SPX","NDX"],"scheduled":true},{"t":1758312000,"category":"market-structure","title":"Triple witching","assets":["SPX","NDX"],"scheduled":true},{"t":1760731200,"category":"market-structure","title":"Monthly options expiry (OpEx)","assets":["SPX","NDX"],"scheduled":true},{"t":1763755200,"category":"market-structure","title":"Monthly options expiry (OpEx)","assets":["SPX","NDX"],"scheduled":true},{"t":1766174400,"category":"market-structure","title":"Triple witching","assets":["SPX","NDX"],"scheduled":true},{"t":1768593600,"category":"market-structure","title":"Monthly options expiry (OpEx)","assets":["SPX","NDX"],"scheduled":true},{"t":1771617600,"category":"market-structure","title":"Monthly options expiry (OpEx)","assets":["SPX","NDX"],"scheduled":true},{"t":1774036800,"category":"market-structure","title":"Triple witching","assets":["SPX","NDX"],"scheduled":true},{"t":1776456000,"category":"market-structure","title":"Monthly options expiry (OpEx)","assets":["SPX","NDX"],"scheduled":true},{"t":1778875200,"category":"market-structure","title":"Monthly options expiry (OpEx)","assets":["SPX","NDX"],"scheduled":true},{"t":1781899200,"category":"market-structure","title":"Triple witching","assets":["SPX","NDX"],"scheduled":true},{"t":1753898400,"category":"monetary-policy","title":"FOMC rate decision","assets":["US10Y","US2Y","USD","EURUSD","SPX","NDX","XLK","SMH","VIX","GOLD","BTC"],"scheduled":true},{"t":1758132000,"category":"monetary-policy","title":"FOMC rate decision","assets":["US10Y","US2Y","USD","EURUSD","SPX","NDX","XLK","SMH","VIX","GOLD","BTC"],"scheduled":true},{"t":1761760800,"category":"monetary-policy","title":"FOMC rate decision","assets":["US10Y","US2Y","USD","EURUSD","SPX","NDX","XLK","SMH","VIX","GOLD","BTC"],"scheduled":true},{"t":1765389600,"category":"monetary-policy","title":"FOMC rate decision","assets":["US10Y","US2Y","USD","EURUSD","SPX","NDX","XLK","SMH","VIX","GOLD","BTC"],"scheduled":true},{"t":1769623200,"category":"monetary-policy","title":"FOMC rate decision","assets":["US10Y","US2Y","USD","EURUSD","SPX","NDX","XLK","SMH","VIX","GOLD","BTC"],"scheduled":true},{"t":1773856800,"category":"monetary-policy","title":"FOMC rate decision","assets":["US10Y","US2Y","USD","EURUSD","SPX","NDX","XLK","SMH","VIX","GOLD","BTC"],"scheduled":true},{"t":1777485600,"category":"monetary-policy","title":"FOMC rate decision","assets":["US10Y","US2Y","USD","EURUSD","SPX","NDX","XLK","SMH","VIX","GOLD","BTC"],"scheduled":true},{"t":1781719200,"category":"monetary-policy","title":"FOMC rate decision","assets":["US10Y","US2Y","USD","EURUSD","SPX","NDX","XLK","SMH","VIX","GOLD","BTC"],"scheduled":true},{"t":1753358400,"category":"monetary-policy","title":"ECB rate decision","assets":["EURUSD","USD","GOLD","SPX","XLK","VIX"],"scheduled":true},{"t":1757592000,"category":"monetary-policy","title":"ECB rate decision","assets":["EURUSD","USD","GOLD","SPX","XLK","VIX"],"scheduled":true},{"t":1761825600,"category":"monetary-policy","title":"ECB rate decision","assets":["EURUSD","USD","GOLD","SPX","XLK","VIX"],"scheduled":true},{"t":1766059200,"category":"monetary-policy","title":"ECB rate decision","assets":["EURUSD","USD","GOLD","SPX","XLK","VIX"],"scheduled":true},{"t":1769688000,"category":"monetary-policy","title":"ECB rate decision","assets":["EURUSD","USD","GOLD","SPX","XLK","VIX"],"scheduled":true},{"t":1773316800,"category":"monetary-policy","title":"ECB rate decision","assets":["EURUSD","USD","GOLD","SPX","XLK","VIX"],"scheduled":true},{"t":1776340800,"category":"monetary-policy","title":"ECB rate decision","assets":["EURUSD","USD","GOLD","SPX","XLK","VIX"],"scheduled":true},{"t":1780574400,"category":"monetary-policy","title":"ECB rate decision","assets":["EURUSD","USD","GOLD","SPX","XLK","VIX"],"scheduled":true},{"t":1753963200,"category":"monetary-policy","title":"Bank of Japan decision","assets":["USD","SPX","NDX","XLK","GOLD","VIX"],"scheduled":true},{"t":1758283200,"category":"monetary-policy","title":"Bank of Japan decision","assets":["USD","SPX","NDX","XLK","GOLD","VIX"],"scheduled":true},{"t":1761825600,"category":"monetary-policy","title":"Bank of Japan decision","assets":["USD","SPX","NDX","XLK","GOLD","VIX"],"scheduled":true},{"t":1766145600,"category":"monetary-policy","title":"Bank of Japan decision","assets":["USD","SPX","NDX","XLK","GOLD","VIX"],"scheduled":true},{"t":1769169600,"category":"monetary-policy","title":"Bank of Japan decision","assets":["USD","SPX","NDX","XLK","GOLD","VIX"],"scheduled":true},{"t":1773835200,"category":"monetary-policy","title":"Bank of Japan decision","assets":["USD","SPX","NDX","XLK","GOLD","VIX"],"scheduled":true},{"t":1777377600,"category":"monetary-policy","title":"Bank of Japan decision","assets":["USD","SPX","NDX","XLK","GOLD","VIX"],"scheduled":true},{"t":1781611200,"category":"monetary-policy","title":"Bank of Japan decision","assets":["USD","SPX","NDX","XLK","GOLD","VIX"],"scheduled":true},{"t":1750872944,"category":"lunar","title":"New moon","assets":["SPX","NDX","BTC"],"scheduled":true},{"t":1753424386,"category":"lunar","title":"New moon","assets":["SPX","NDX","BTC"],"scheduled":true},{"t":1755975829,"category":"lunar","title":"New moon","assets":["SPX","NDX","BTC"],"scheduled":true},{"t":1758527272,"category":"lunar","title":"New moon","assets":["SPX","NDX","BTC"],"scheduled":true},{"t":1761078715,"category":"lunar","title":"New moon","assets":["SPX","NDX","BTC"],"scheduled":true},{"t":1763630158,"category":"lunar","title":"New moon","assets":["SPX","NDX","BTC"],"scheduled":true},{"t":1766181601,"category":"lunar","title":"New moon","assets":["SPX","NDX","BTC"],"scheduled":true},{"t":1768733044,"category":"lunar","title":"New moon","assets":["SPX","NDX","BTC"],"scheduled":true},{"t":1771284487,"category":"lunar","title":"New moon","assets":["SPX","NDX","BTC"],"scheduled":true},{"t":1773835929,"category":"lunar","title":"New moon","assets":["SPX","NDX","BTC"],"scheduled":true},{"t":1776387372,"category":"lunar","title":"New moon","assets":["SPX","NDX","BTC"],"scheduled":true},{"t":1778938815,"category":"lunar","title":"New moon","assets":["SPX","NDX","BTC"],"scheduled":true},{"t":1781490258,"category":"lunar","title":"New moon","assets":["SPX","NDX","BTC"],"scheduled":true},{"t":1752148665,"category":"lunar","title":"Full moon","assets":["SPX","NDX","BTC","GOLD"],"scheduled":true},{"t":1754700108,"category":"lunar","title":"Full moon","assets":["SPX","NDX","BTC","GOLD"],"scheduled":true},{"t":1757251551,"category":"lunar","title":"Full moon","assets":["SPX","NDX","BTC","GOLD"],"scheduled":true},{"t":1759802994,"category":"lunar","title":"Full moon","assets":["SPX","NDX","BTC","GOLD"],"scheduled":true},{"t":1762354436,"category":"lunar","title":"Full moon","assets":["SPX","NDX","BTC","GOLD"],"scheduled":true},{"t":1764905879,"category":"lunar","title":"Full moon","assets":["SPX","NDX","BTC","GOLD"],"scheduled":true},{"t":1767457322,"category":"lunar","title":"Full moon","assets":["SPX","NDX","BTC","GOLD"],"scheduled":true},{"t":1770008765,"category":"lunar","title":"Full moon","assets":["SPX","NDX","BTC","GOLD"],"scheduled":true},{"t":1772560208,"category":"lunar","title":"Full moon","assets":["SPX","NDX","BTC","GOLD"],"scheduled":true},{"t":1775111651,"category":"lunar","title":"Full moon","assets":["SPX","NDX","BTC","GOLD"],"scheduled":true},{"t":1777663094,"category":"lunar","title":"Full moon","assets":["SPX","NDX","BTC","GOLD"],"scheduled":true},{"t":1780214537,"category":"lunar","title":"Full moon","assets":["SPX","NDX","BTC","GOLD"],"scheduled":true}]
